{
    "Client": {
        "transaction": false,
        "transactions": false,
        "wallet": true,
        "wallets": false,
        "delegate": false,
        "delegates": false,
        "votes": false,
        "voters": false,
        "configuration": false,
        "fees": false,
        "syncing": false,
        "broadcast": false
    },
    "Fee": {
        "all": false
    },
    "Identity": {
        "address": {
            "mnemonic": true,
            "multiSignature": false,
            "publicKey": true,
            "privateKey": false,
            "wif": false,
            "validate": true
        },
        "publicKey": {
            "mnemonic": true,
            "multiSignature": false,
            "wif": false
        },
        "privateKey": {
            "mnemonic": true,
            "wif": false
        },
        "wif": {
            "mnemonic": false
        },
        "keyPair": {
            "mnemonic": true,
            "privateKey": true,
            "wif": false
        }
    },
    "Ledger": {
        "getVersion": false,
        "getPublicKey": false,
        "signTransaction": false,
        "signMessage": false
    },
    "Link": {
        "block": true,
        "transaction": true,
        "wallet": true
    },
    "Message": {
        "sign": true,
        "verify": true
    },
    "Peer": {
        "search": false
    },
    "Transaction": {
        "transfer": true,
        "secondSignature": false,
        "delegateRegistration": false,
        "vote": false,
        "multiSignature": false,
        "ipfs": false,
        "multiPayment": false,
        "delegateResignation": false,
        "htlcLock": false,
        "htlcClaim": false,
        "htlcRefund": false
    },
    "Miscellaneous": {
        "dynamicFees": false,
        "memo": false,
        "utxo": true
    },
    "Derivation": {
        "bip39": true,
        "bip44": true,
        "bip49": false,
        "bip84": false
    }
}
